{
  "trained_at": "2026-06-30T07:36:05.778024",
  "mode": "daily_warm_start",
  "accuracy": 0.6111,
  "auc": 0.7808,
  "n_samples": 177,
  "feature_importance": {
    "bb_width": 43.74,
    "bb_pos": 40.67,
    "vol_trend_5d": 29.82,
    "momentum_accel_3d": 26.92,
    "upper_shadow": 26.58,
    "ret_10d": 26.51,
    "adx": 24.82,
    "ma60_ratio": 22.72,
    "stoch_k": 17.33,
    "ret_5d": 12.94,
    "ma5_20_cross": 11.1,
    "atr_ratio": 11.09,
    "vol_ma20_ratio": 10.72,
    "ret_3d": 10.08,
    "day_of_week": 9.82,
    "di_plus": 5.92,
    "price_position_20d": 5.31,
    "macd_hist": 4.22,
    "obv_slope_10": 3.59,
    "body_ratio": 0.25
  }
}